data_detail/__init__.py
data_detail/dd.py
data_detail-2.12.22.dist-info/METADATA
data_detail-2.12.22.dist-info/WHEEL
data_detail-2.12.22.dist-info/top_level.txt
data_detail-2.12.22.dist-info/RECORD
