Metadata-Version: 2.1
Name: data-detail
Version: 2.12.22
Summary: :data: input dataset name
Home-page: https://github.com/Waiz-Legion/
Author: Waiz Khan
Author-email: waizk447@gmail.com
License: MIT
Platform: UNKNOWN
Classifier: Programming Language :: Python :: 3
Classifier: License :: OSI Approved :: MIT License
Classifier: Operating System :: OS Independent
Requires-Dist: pandas
